com/__init__.py
com/lw/__init__.py
com/lw/data.py
com/lw/message.py
com_lw-0.0.1.dist-info/METADATA
com_lw-0.0.1.dist-info/WHEEL
com_lw-0.0.1.dist-info/top_level.txt
com_lw-0.0.1.dist-info/RECORD
