Metadata-Version: 2.4
Name: com.lw
Version: 0.0.1
Summary: Get test Information.
Home-page: http://www.lw.com
Author: LW
Classifier: Environment :: Web Environment
Classifier: Intended Audience :: Developers
Classifier: License :: OSI Approved :: BSD License
Classifier: Operating System :: OS Independent
Classifier: Programming Language :: Python
Classifier: Programming Language :: Python :: 2
Classifier: Programming Language :: Python :: 3
Dynamic: author
Dynamic: classifier
Dynamic: description
Dynamic: home-page
Dynamic: summary
